{
    "KCBN_HY_1": [
        {
            "name": "**NewJeans Hyein**",
            "image": "https://ihwannieu.sirv.com/machubot/cards/k_common/hyein/HY_K_1.png?format=png",
            "theme": "Bunny",
            "inv": "<:kgray:1105400337847816202> Bunny",
            "grade": "<:kgray:1105400337847816202> K-Common, <:1stamp:1105400920646361088> 1 stamp",
            "code": "`KCBN_HY_1`"
        }
    ],
    "KCBN_HY_2": [
        {
            "name": "**NewJeans Hyein**",
            "image": "https://ihwannieu.sirv.com/machubot/cards/k_common/hyein/HY_K_2.png?format=png",
            "theme": "Bunny",
            "inv": "<:kblue:1105400582321213440> Bunny",
            "grade": "<:kblue:1105400582321213440> K-Common, <:2stamps:1105401031292108830> 2 stamps",
            "code": "`KCBN_HY_2`"
        }
    ],
    "KCBN_HY_3": [
        {
            "name": "**NewJeans Hyein**",
            "image": "https://ihwannieu.sirv.com/machubot/cards/k_common/hyein/HY_K_3.png?format=png",
            "theme": "Bunny",
            "inv": "<:kviolet:1105400753650155550> Bunny",
            "grade": "<:kviolet:1105400753650155550> K-Common, <:3stamps:1105401134279032884> 3 stamps",
            "code": "`KCBN_HY_3`"
        }
    ],
    "KCFR_EC_1": [
        {
            "name": "**LE SSERAFIM Eunchae**",
            "image": "https://ihwannieu.sirv.com/machubot/cards/k_common/eunchae/K_EC_1.png?format=png",
            "theme": "Fries",
            "inv": "<:kgray:1105400337847816202> Fries",
            "grade": "<:kgray:1105400337847816202> K-Common, <:1stamp:1105400920646361088> 1 stamp",
            "code": "`KCFR_EC_1`"
        }
    ],
    "KCFR_EC_2": [
        {
            "name": "**LE SSERAFIM Eunchae**",
            "image": "https://ihwannieu.sirv.com/machubot/cards/k_common/eunchae/K_EC_2.png?format=png",
            "theme": "Fries",
            "inv": "<:kblue:1105400582321213440> Fries",
            "grade": "<:kblue:1105400582321213440> K-Common, <:2stamps:1105401031292108830> 2 stamps",
            "code": "`KCFR_EC2`"
        }
    ],
    "KCFR_EC_3": [
        {
            "name": "**LE SSERAFIM Eunchae**",
            "image": "https://ihwannieu.sirv.com/machubot/cards/k_common/eunchae/K_EC_3.png?format=png",
            "theme": "Fries",
            "inv": "<:kviolet:1105400753650155550> Fries",
            "grade": "<:kviolet:1105400753650155550> K-Common, <:3stamps:1105401134279032884> 3 stamps",
            "grade": "`KCFR_EC3`"
        }
    ],
    "KCAN_LI_1": [
        {
            "name": "**IVE Liz**",
            "image": "https://ihwannieu.sirv.com/machubot/cards/k_common/liz/K_LI_1.png?format=png",
            "theme": "Annyeong",
            "inv": "<:kgray:1105400337847816202> Annyeong",
            "grade": "<:kgray:1105400337847816202> K-Common, <:1stamp:1105400920646361088> 1 stamp",
            "code": "`KCAN_LI_1`"
        }
    ],
    "KCAN_LI_2": [
        {
            "name": "**IVE Liz**",
            "image": "https://ihwannieu.sirv.com/machubot/cards/k_common/liz/K_LI_2.png?format=png",
            "theme": "Annyeong",
            "inv": "<:kblue:1105400582321213440> Annyeong",
            "grade": "<:kblue:1105400582321213440> K-Common, <:2stamps:1105401031292108830> 2 stamps",
            "code" : "`KCAN_LI_2`"
        }
    ],
    "KCAN_LI_3": [
        {
            "name": "**IVE Liz**",
            "image": "https://ihwannieu.sirv.com/machubot/cards/k_common/liz/K_LI_3.png?format=png",
            "theme": "Annyeong",
            "inv": "<:kviolet:1105400753650155550> Annyeong",
            "grade": "<:kviolet:1105400753650155550> K-Common, <:3stamps:1105401134279032884> 3 stamps",
            "code": "`KCAN_LI_3`"
        }
    ],
    "KCWC_WY_1": [
        {
            "name": "**IVE Wonyoung**",
            "image": "https://ihwannieu.sirv.com/machubot/cards/k_common/wonyoung/KC_WY_1.png?format=png",
            "theme": "Annyeong",
            "inv": "<:kgray:1105400337847816202> Annyeong",
            "grade": "<:kgray:1105400337847816202> K-Common, <:1stamp:1105400920646361088> 1 stamp",
            "code": "`KCWC_WY_1`"
        }
    ],
    "KCWC_WY_2": [
        {
            "name": "**IVE Wonyoung**",
            "image": "https://ihwannieu.sirv.com/machubot/cards/k_common/wonyoung/KC_WY_2.png?format=png",
            "theme": "White Cap",
            "inv": "<:kblue:1105400582321213440> White Cap",
            "grade": "<:kblue:1105400582321213440> K-Common, <:2stamps:1105401031292108830> 2 stamps",
            "code" : "`KCWC_WY_2`"
        }
    ],
    "KCWC_WY_3": [
        {
            "name": "**IVE Wonyoung**",
            "image": "https://ihwannieu.sirv.com/machubot/cards/k_common/wonyoung/KC_WY_3.png?format=png",
            "theme": "White Cap",
            "inv": "<:kviolet:1105400753650155550> White Cap",
            "grade": "<:kviolet:1105400753650155550> K-Common, <:3stamps:1105401134279032884> 3 stamps",
            "code": "`KCWC_WY_3`"
        }
    ],
    "KCPP_JH_1": [
        {
            "name": "**TREASURE Junghwan**",
            "image": "https://ihwannieu.sirv.com/machubot/cards/k_common/junghwan/KC_JH_1.png?format=png",
            "theme": "Pout+Peace",
            "inv": "<:kgray:1105400337847816202> Pout+Peace",
            "grade": "<:kgray:1105400337847816202> K-Common, <:1stamp:1105400920646361088> 1 stamp",
            "code": "`KCPP_JH_1`"
        }
    ],
    "KCPP_JH_2": [
        {
            "name": "**TREASURE Junghwan**",
            "image": "https://ihwannieu.sirv.com/machubot/cards/k_common/junghwan/KC_JH_2.png?format=png",
            "theme": "Pout+Peace",
            "inv": "<:kblue:1105400582321213440> Pout+Peace",
            "grade": "<:kblue:1105400582321213440> K-Common, <:2stamps:1105401031292108830> 2 stamps",
            "code" : "`KCPP_JH_2`"
        }
    ],
    "KCPP_JH_3": [
        {
            "name": "**TREASURE Junghwan**",
            "image": "https://ihwannieu.sirv.com/machubot/cards/k_common/junghwan/KC_JH_3.png?format=png",
            "theme": "Pout+Peace",
            "inv": "<:kviolet:1105400753650155550> Pout+Peace",
            "grade": "<:kviolet:1105400753650155550> K-Common, <:3stamps:1105401134279032884> 3 stamps",
            "code": "`KCPP_JH_3`"
        }
    ],
    "KCPE_JI_1": [
        {
            "name": "**TREASURE Jihoon**",
            "image": "https://ihwannieu.sirv.com/machubot/cards/k_common/jihoon/KC_JI_1.png?format=png",
            "theme": "Peace",
            "inv": "<:kgray:1105400337847816202> Peace",
            "grade": "<:kgray:1105400337847816202> K-Common, <:1stamp:1105400920646361088> 1 stamp",
            "code": "`KCPE_JI_1`"
        }
    ],
    "KCPE_JI_2": [
        {
            "name": "**TREASURE Jihoon**",
            "image": "https://ihwannieu.sirv.com/machubot/cards/k_common/jihoon/KC_JI_2.png?format=png",
            "theme": "Peace",
            "inv": "<:kblue:1105400582321213440> Peace",
            "grade": "<:kblue:1105400582321213440> K-Common, <:2stamps:1105401031292108830> 2 stamps",
            "code" : "`KCPE_JI_2`"
        }
    ],
    "KCPE_JI_3": [
        {
            "name": "**TREASURE Jihoon**",
            "image": "https://ihwannieu.sirv.com/machubot/cards/k_common/jihoon/KC_JI_3.png?format=png",
            "theme": "Peace",
            "inv": "<:kviolet:1105400753650155550> Peace",
            "grade": "<:kviolet:1105400753650155550> K-Common, <:3stamps:1105401134279032884> 3 stamps",
            "code": "`KCPE_JI_3`"
        }
    ],
    "KCBS_JK_1": [
        {
            "name": "**ENHYPEN Jake**",
            "image": "https://ihwannieu.sirv.com/machubot/cards/k_common/jake/KC_JK_1.png?format=png",
            "theme": "Bed Selca",
            "inv": "<:kgray:1105400337847816202> Bed Selca",
            "grade": "<:kgray:1105400337847816202> K-Common, <:1stamp:1105400920646361088> 1 stamp",
            "code": "`KCBS_JK_1`"
        }
    ],
    "KCBS_JK_2": [
        {
            "name": "**ENHYPEN Jake**",
            "image": "https://ihwannieu.sirv.com/machubot/cards/k_common/jake/KC_JK_2.png?format=png",
            "theme": "Bed Selca",
            "inv": "<:kblue:1105400582321213440> Bed Selca",
            "grade": "<:kblue:1105400582321213440> K-Common, <:2stamps:1105401031292108830> 2 stamps",
            "code" : "`KCBS_JK_2`"
        }
    ],
    "KCBS_JK_3": [
        {
            "name": "**ENHYPEN Jake**",
            "image": "https://ihwannieu.sirv.com/machubot/cards/k_common/jake/KC_JK_3.png?format=png",
            "theme": "Bed Selca",
            "inv": "<:kviolet:1105400753650155550> Bed Selca",
            "grade": "<:kviolet:1105400753650155550> K-Common, <:3stamps:1105401134279032884> 3 stamps",
            "code": "`KCBS_JK_3`"
        }
    ],
    "KCBR_DY_1": [
        {
            "name": "**TREASURE Doyoung**",
            "image": "https://ihwannieu.sirv.com/machubot/cards/k_common/doyoung/KC_DY_1.png?format=png",
            "theme": "BBIROTONGTONG",
            "inv": "<:kgray:1105400337847816202> BBIROTONGTONG",
            "grade": "<:kgray:1105400337847816202> K-Common, <:1stamp:1105400920646361088> 1 stamp",
            "code": "`KCBR_DY_1`"
        }
    ],
    "KCBR_DY_2": [
        {
            "name": "**TREASURE Doyoung**",
            "image": "https://ihwannieu.sirv.com/machubot/cards/k_common/doyoung/KC_DY_2.png?format=png",
            "theme": "BBIROTONGTONG",
            "inv": "<:kblue:1105400582321213440> BBIROTONGTONG",
            "grade": "<:kblue:1105400582321213440> K-Common, <:2stamps:1105401031292108830> 2 stamps",
            "code" : "`KCBR_DY_2`"
        }
    ],
    "KCBR_DY_3": [
        {
            "name": "**TREASURE Doyoung**",
            "image": "https://ihwannieu.sirv.com/machubot/cards/k_common/doyounh/KC_DY_3.png?format=png",
            "theme": "BBIROTONGTONG",
            "inv": "<:kviolet:1105400753650155550> BBIROTONGTONG",
            "grade": "<:kviolet:1105400753650155550> K-Common, <:3stamps:1105401134279032884> 3 stamps",
            "code": "`KCBR_DY_3`"
        }
    ],
    "ZBZH_CG_1": [
        {
            "name": "**ZB1 Zhanghao**",
            "image": "https://ihwannieu.sirv.com/machubot/cards/cards2/zhanghao/ZHCV_1.png?format=png",
            "inv": "<:starla:1106508251853508688> BOYS PLANET CGV",
            "code": "`ZBZH_CG_1`"
        }
    ],
    "ZBZH_CG_2": [
        {
            "name": "**ZB1 Zhanghao**",
            "image": "https://ihwannieu.sirv.com/machubot/cards/cards2/zhanghao/ZHCV_2.png?format=png",
            "inv": "<:starla:1106508251853508688><:starla:1106508251853508688> BOYS PLANET CGV",
            "code": "`ZBZH_CG_2`"
        }
    ],
    "ZBZH_CG_3": [
        {
            "name": "**ZB1 Zhanghao**",
            "image": "https://ihwannieu.sirv.com/machubot/cards/cards2/zhanghao/ZHCV_3.png?format=png",
            "inv": "<:starla:1106508251853508688><:starla:1106508251853508688><:starla:1106508251853508688> BOYS PLANET CGV",
            "code": "`ZBZH_CG_3`"
        }
    ],
    "TWNY_HE_1": [
        {
            "name": "**TWICE Nayeon**",
            "image": "https://ihwannieu.sirv.com/machubot/cards/cards2/nayeon/TWNY_1.png?format=png",
            "inv": "<:starla:1106508251853508688> NAYEON SELCA",
            "code": "`TWNY_HE_1`"
        }
    ],
    "TWNY_HE_2": [
        {
            "name": "**TWICE Nayeon**",
            "image": "https://ihwannieu.sirv.com/machubot/cards/cards2/nayeon/TWNY_2.png?format=png",
            "inv": "<:starla:1106508251853508688><:starla:1106508251853508688> NAYEON SELCA",
            "code": "`TWNY_HE_2`"
        }
    ],
    "TWNY_HE_3": [
        {
            "name": "**TWICE Nayeon**",
            "image": "https://ihwannieu.sirv.com/machubot/cards/cards2/nayeon/TWNY_3.png?format=png",
            "inv": "<:starla:1106508251853508688><:starla:1106508251853508688><:starla:1106508251853508688> NAYEON SELCA",
            "code": "`TWNY_HE_3`"
        }
    ],
    "TWMN_PL_1": [
        {
            "name": "**TWICE Mina**",
            "image": "https://ihwannieu.sirv.com/machubot/cards/cards2/mina/TWMN_1.png?format=png",
            "inv": "<:starla:1106508251853508688> MINA SELCA",
            "code": "`TWMN_PL_1`"
        }
    ],
    "TWMN_PL_2": [
        {
            "name": "**TWICE Mina**",
            "image": "https://ihwannieu.sirv.com/machubot/cards/cards2/mina/TWMN_2.png?format=png",
            "inv": "<:starla:1106508251853508688><:starla:1106508251853508688> MINA SELCA",
            "code": "`TWMN_PL_2`"
        }
    ],
    "TWMN_PL_3": [
        {
            "name": "**TWICE Mina**",
            "image": "https://ihwannieu.sirv.com/machubot/cards/cards2/mina/TWMN_3.png?format=png",
            "inv": "<:starla:1106508251853508688><:starla:1106508251853508688><:starla:1106508251853508688> MINA SELCA",
            "code": "`TWMN_PL_3`"
        }
    ],
    "LSYJ_AF_1": [
        {
            "name": "**LE SSERAFIM Yunjin**",
            "image": "https://ihwannieu.sirv.com/machubot/cards/cards2/yunjin/LSYJ_1.png?format=png",
            "inv": "<:starla:1106508251853508688> LE SSERAFIM ANTIFRAGILE",
            "code": "`LSYJ_AF_1`"
        }
    ],
    "LSYJ_AF_2": [
        {
            "name": "**LE SSERAFIM Yunjin**",
            "image": "https://ihwannieu.sirv.com/machubot/cards/cards2/yunjin/LSYJ_2.png?format=png",
            "inv": "<:starla:1106508251853508688><:starla:1106508251853508688> LE SSERAFIM ANTIFRAGILE",
            "code": "`LSYJ_AF_2`"
        }
    ],
    "LSYJ_AF_3": [
        {
            "name": "**LE SSERAFIM Yunjin**",
            "image": "https://ihwannieu.sirv.com/machubot/cards/cards2/yunjin/LSYJ_3.png?format=png",
            "inv": "<:starla:1106508251853508688><:starla:1106508251853508688><:starla:1106508251853508688> LE SSERAFIM ANTIFRAGILE",
            "code": "`LSYJ_AF_3`"
        }
    ],
    "ZBTR_CG_1": [
        {
            "name": "**ZB1 Taerae**",
            "image": "https://ihwannieu.sirv.com/machubot/cards/cards2/taerae/ZBTR_1.png?format=png",
            "inv": "<:starla:1106508251853508688> BOYS PLANET CGV",
            "code": "`ZBTR_CG_1`"
        }
    ],
    "ZBTR_CG_2": [
        {
            "name": "**ZB1 Taerae**",
            "image": "https://ihwannieu.sirv.com/machubot/cards/cards2/taerae/ZBTR_2.png?format=png",
            "inv": "<:starla:1106508251853508688><:starla:1106508251853508688> BOYS PLANET CGV",
            "code": "`ZBTR_CG_2`"
        }
    ],
    "ZBTR_CG_3": [
        {
            "name": "**ZB1 Taerae**",
            "image": "https://ihwannieu.sirv.com/machubot/cards/cards2/taerae/ZBTR_3.png?format=png",
            "inv": "<:starla:1106508251853508688><:starla:1106508251853508688><:starla:1106508251853508688> BOYS PLANET CGV",
            "code": "`ZBTR_CG_3`"
        }
    ],
    "TRJW_ST_1": [
        {
            "name": "**TREASURE Jeongwoo**",
            "image": "https://ihwannieu.sirv.com/machubot/cards/cards2/jeongwoo/TRJW_1.png?format=png",
            "inv": "<:starla:1106508251853508688> JEONGWOO STUDIO SELCA",
            "code": "`TRJW_ST_1`"
        }
    ],
    "TRJW_ST_2": [
        {
            "name": "**TREASURE Jeongwoo**",
            "image": "https://ihwannieu.sirv.com/machubot/cards/cards2/jeongwoo/TRJW_2.png?format=png",
            "inv": "<:starla:1106508251853508688><:starla:1106508251853508688> JEONGWOO STUDIO SELCA",
            "code": "`TRJW_ST_2`"
        }
    ],
    "TRJW_ST_3": [
        {
            "name": "**TREASURE Jeongwoo**",
            "image": "https://ihwannieu.sirv.com/machubot/cards/cards2/jeongwoo/TRJW_3.png?format=png",
            "inv": "<:starla:1106508251853508688><:starla:1106508251853508688><:starla:1106508251853508688> JEONGWOO STUDIO SELCA",
            "code": "`TRJW_ST_3`"
        }
    ],
    "NJHR_OM_1": [
        {
            "name": "**NewJeans Haerin**",
            "image": "https://ihwannieu.sirv.com/machubot/cards/cards2/jeongwoo/TRJW_1.png?format=png",
            "inv": "<:starla:1106508251853508688> HAERIN OMG ERA",
            "code": "`NJHR_OM_1`"
        }
    ],
    "NJHR_OM_2": [
        {
            "name": "**NewJeans Haerin**",
            "image": "https://ihwannieu.sirv.com/machubot/cards/cards2/jeongwoo/TRJW_2.png?format=png",
            "inv": "<:starla:1106508251853508688><:starla:1106508251853508688> HAERIN OMG ERA",
            "code": "`NJHR_OM_2`"
        }
    ],
    "NJHR_OM_3": [
        {
            "name": "**NewJeans Haerin**",
            "image": "https://ihwannieu.sirv.com/machubot/cards/cards2/jeongwoo/TRJW_3.png?format=png",
            "inv": "<:starla:1106508251853508688><:starla:1106508251853508688><:starla:1106508251853508688> HAERIN OMG ERA",
            "code": "`NJHR_OM_3`"
        }
    ],
